jsp/__init__.py
jsp/test_input.py
jsp-0.8.6.dist-info/LICENSE
jsp-0.8.6.dist-info/METADATA
jsp-0.8.6.dist-info/WHEEL
jsp-0.8.6.dist-info/entry_points.txt
jsp-0.8.6.dist-info/top_level.txt
jsp-0.8.6.dist-info/RECORD
